getwallpapers/__init__.py
getwallpapers/__main__.py
getwallpapers/getwallpapers.py
getwallpapers-0.1.1.dist-info/LICENSE
getwallpapers-0.1.1.dist-info/METADATA
getwallpapers-0.1.1.dist-info/WHEEL
getwallpapers-0.1.1.dist-info/top_level.txt
getwallpapers-0.1.1.dist-info/RECORD
