Metadata-Version: 2.1
Name: getwallpapers
Version: 0.1.1
Summary: download wallpaper collection from http://getwallpapers.com/
Home-page: https://github.com/falcon-head/getwallpapers-downloader
Author: Shrikrishna Joisa
Author-email: shrikrishnajois@gmail.com
License: MIT
Platform: Any
Classifier: Development Status :: 3 - Alpha
Classifier: License :: OSI Approved :: MIT License
Classifier: Operating System :: OS Independent
Classifier: Programming Language :: Python
Requires-Dist: beautifulsoup4
Requires-Dist: tqdm
Requires-Dist: urllib3
